LICENCE
README.md
X_创作号拉齐宽表.csv
setup.py
拉齐创作号方法说明.docx
.idea/.gitignore
.idea/match_group_model.iml
.idea/misc.xml
.idea/modules.xml
.idea/vcs.xml
.idea/inspectionProfiles/profiles_settings.xml
matchgroup/__init__.py
matchgroup/psm_two_group.py
matchgroup.egg-info/PKG-INFO
matchgroup.egg-info/SOURCES.txt
matchgroup.egg-info/dependency_links.txt
matchgroup.egg-info/requires.txt
matchgroup.egg-info/top_level.txt