Metadata-Version: 2.1
Name: matchgroup
Version: 0.0.1
Summary: package for matching creators with PSM
Home-page: https://git.woa.com/content_supply_chain/match_group_model
Author: wufeipku
Author-email: wufei.pku@163.com
Classifier: Programming Language :: Python :: 3
Classifier: License :: OSI Approved :: MIT License
Classifier: Operating System :: OS Independent
License-File: LICENCE
